{
    "file_name": "000000308752.jpg",
    "generator": "convert_to_region_cropper.py",
    "labels": [
        "position",
        "left_eye",
        "right_eye",
        "left_cheek",
        "right_cheek",
        "nose_base",
        "left_mouth",
        "right_mouth",
        "bottom_mouth"
    ],
    "regions": [
        {
            "label": 0,
            "probability": 0.999,
            "rect": {
                "bottom": 0.51171875,
                "left": 0.5078125,
                "right": 0.64453125,
                "top": 0.3359375
            }
        },
        {
            "label": 1,
            "probability": 0.999,
            "rect": {
                "bottom": 0.42638308,
                "left": 0.59736127,
                "right": 0.59736127,
                "top": 0.42638308
            }
        },
        {
            "label": 2,
            "probability": 0.999,
            "rect": {
                "bottom": 0.43164575,
                "left": 0.5605959,
                "right": 0.5605959,
                "top": 0.43164575
            }
        },
        {
            "label": 3,
            "probability": 0.999,
            "rect": {
                "bottom": 0.45466605,
                "left": 0.55570555,
                "right": 0.55570555,
                "top": 0.45466605
            }
        },
        {
            "label": 4,
            "probability": 0.999,
            "rect": {
                "bottom": 0.44996387,
                "left": 0.60144985,
                "right": 0.60144985,
                "top": 0.44996387
            }
        },
        {
            "label": 5,
            "probability": 0.999,
            "rect": {
                "bottom": 0.46149337,
                "left": 0.57742566,
                "right": 0.57742566,
                "top": 0.46149337
            }
        },
        {
            "label": 6,
            "probability": 0.999,
            "rect": {
                "bottom": 0.4791888,
                "left": 0.5995694,
                "right": 0.5995694,
                "top": 0.4791888
            }
        },
        {
            "label": 7,
            "probability": 0.999,
            "rect": {
                "bottom": 0.4808726,
                "left": 0.5643068,
                "right": 0.5643068,
                "top": 0.4808726
            }
        },
        {
            "label": 8,
            "probability": 0.999,
            "rect": {
                "bottom": 0.4935361,
                "left": 0.58331645,
                "right": 0.58331645,
                "top": 0.4935361
            }
        },
        {
            "label": 0,
            "probability": 0.999,
            "rect": {
                "bottom": 0.6640625,
                "left": 0.66015625,
                "right": 0.796875,
                "top": 0.49609375
            }
        },
        {
            "label": 1,
            "probability": 0.999,
            "rect": {
                "bottom": 0.58641326,
                "left": 0.75230634,
                "right": 0.75230634,
                "top": 0.58641326
            }
        },
        {
            "label": 2,
            "probability": 0.999,
            "rect": {
                "bottom": 0.5853896,
                "left": 0.72106445,
                "right": 0.72106445,
                "top": 0.5853896
            }
        },
        {
            "label": 4,
            "probability": 0.999,
            "rect": {
                "bottom": 0.602121,
                "left": 0.7774198,
                "right": 0.7774198,
                "top": 0.602121
            }
        },
        {
            "label": 5,
            "probability": 0.999,
            "rect": {
                "bottom": 0.62305313,
                "left": 0.72919947,
                "right": 0.72919947,
                "top": 0.62305313
            }
        },
        {
            "label": 6,
            "probability": 0.999,
            "rect": {
                "bottom": 0.6378223,
                "left": 0.7548537,
                "right": 0.7548537,
                "top": 0.6378223
            }
        },
        {
            "label": 8,
            "probability": 0.999,
            "rect": {
                "bottom": 0.6550379,
                "left": 0.73050845,
                "right": 0.73050845,
                "top": 0.6550379
            }
        }
    ]
}