{
  "updated_at": "2018-08-28T14:54:18.81",
  "generator": "Region Cropper",
  "file_name": "000000077841.jpg",
  "regions": [
    {
      "probability": 1.0,
      "label": 0,
      "rect": {
        "left": 0.10331453,
        "top": 0.25246826,
        "right": 0.24294782,
        "bottom": 0.43300423
      }
    },
    {
      "probability": 0.999,
      "label": 3,
      "rect": {
        "left": 0.427363,
        "top": 0.2434359,
        "right": 0.427363,
        "bottom": 0.2434359
      }
    },
    {
      "probability": 0.999,
      "label": 2,
      "rect": {
        "left": 0.46013802,
        "top": 0.23418832,
        "right": 0.46013802,
        "bottom": 0.23418832
      }
    },
    {
      "probability": 0.999,
      "label": 0,
      "rect": {
        "left": 0.40234375,
        "top": 0.114583336,
        "right": 0.53125,
        "bottom": 0.328125
      }
    },
    {
      "probability": 0.999,
      "label": 7,
      "rect": {
        "left": 0.45474297,
        "top": 0.29619798,
        "right": 0.45474297,
        "bottom": 0.29619798
      }
    },
    {
      "probability": 1.0,
      "label": 0,
      "rect": {
        "left": 0.598378,
        "top": 0.45275036,
        "right": 0.6978138,
        "bottom": 0.5994358
      }
    }
  ],
  "created_at": "2018-08-28T14:54:10.687"
}