{
    "file_name": "000000162559.jpg",
    "generator": "convert_to_region_cropper.py",
    "labels": [
        "position",
        "left_eye",
        "right_eye",
        "left_cheek",
        "right_cheek",
        "nose_base",
        "left_mouth",
        "right_mouth",
        "bottom_mouth"
    ],
    "regions": [
        {
            "label": 0,
            "probability": 0.999,
            "rect": {
                "bottom": 0.4140625,
                "left": 0.1953125,
                "right": 0.33984375,
                "top": 0.23046875
            }
        },
        {
            "label": 2,
            "probability": 0.999,
            "rect": {
                "bottom": 0.3309484,
                "left": 0.24410073,
                "right": 0.24410073,
                "top": 0.3309484
            }
        },
        {
            "label": 3,
            "probability": 0.999,
            "rect": {
                "bottom": 0.3469449,
                "left": 0.21351661,
                "right": 0.21351661,
                "top": 0.3469449
            }
        },
        {
            "label": 5,
            "probability": 0.999,
            "rect": {
                "bottom": 0.3551756,
                "left": 0.2769031,
                "right": 0.2769031,
                "top": 0.3551756
            }
        },
        {
            "label": 0,
            "probability": 0.999,
            "rect": {
                "bottom": 0.3359375,
                "left": 0.44921875,
                "right": 0.74609375,
                "top": 0.0
            }
        },
        {
            "label": 1,
            "probability": 0.999,
            "rect": {
                "bottom": 0.16613328,
                "left": 0.6634248,
                "right": 0.6634248,
                "top": 0.16613328
            }
        },
        {
            "label": 2,
            "probability": 0.999,
            "rect": {
                "bottom": 0.16260968,
                "left": 0.5469061,
                "right": 0.5469061,
                "top": 0.16260968
            }
        },
        {
            "label": 3,
            "probability": 0.999,
            "rect": {
                "bottom": 0.21499601,
                "left": 0.53967994,
                "right": 0.53967994,
                "top": 0.21499601
            }
        },
        {
            "label": 4,
            "probability": 0.999,
            "rect": {
                "bottom": 0.2146408,
                "left": 0.66703,
                "right": 0.66703,
                "top": 0.2146408
            }
        },
        {
            "label": 5,
            "probability": 0.999,
            "rect": {
                "bottom": 0.2251543,
                "left": 0.6019675,
                "right": 0.6019675,
                "top": 0.2251543
            }
        },
        {
            "label": 6,
            "probability": 0.999,
            "rect": {
                "bottom": 0.25712577,
                "left": 0.6447858,
                "right": 0.6447858,
                "top": 0.25712577
            }
        },
        {
            "label": 7,
            "probability": 0.999,
            "rect": {
                "bottom": 0.25813508,
                "left": 0.5525889,
                "right": 0.5525889,
                "top": 0.25813508
            }
        },
        {
            "label": 8,
            "probability": 0.999,
            "rect": {
                "bottom": 0.2756296,
                "left": 0.60041094,
                "right": 0.60041094,
                "top": 0.2756296
            }
        }
    ]
}