{
    "file_name": "000000179699.jpg",
    "generator": "convert_to_region_cropper.py",
    "labels": [
        "position",
        "left_eye",
        "right_eye",
        "left_cheek",
        "right_cheek",
        "nose_base",
        "left_mouth",
        "right_mouth",
        "bottom_mouth"
    ],
    "regions": [
        {
            "label": 0,
            "probability": 0.999,
            "rect": {
                "bottom": 0.40625,
                "left": 0.36328125,
                "right": 0.62890625,
                "top": 0.0
            }
        },
        {
            "label": 1,
            "probability": 0.999,
            "rect": {
                "bottom": 0.19942956,
                "left": 0.5396892,
                "right": 0.5396892,
                "top": 0.19942956
            }
        },
        {
            "label": 2,
            "probability": 0.999,
            "rect": {
                "bottom": 0.19988322,
                "left": 0.45216656,
                "right": 0.45216656,
                "top": 0.19988322
            }
        },
        {
            "label": 3,
            "probability": 0.999,
            "rect": {
                "bottom": 0.25747147,
                "left": 0.44341582,
                "right": 0.44341582,
                "top": 0.25747147
            }
        },
        {
            "label": 4,
            "probability": 0.999,
            "rect": {
                "bottom": 0.25789982,
                "left": 0.5488642,
                "right": 0.5488642,
                "top": 0.25789982
            }
        },
        {
            "label": 5,
            "probability": 0.999,
            "rect": {
                "bottom": 0.27098313,
                "left": 0.49692607,
                "right": 0.49692607,
                "top": 0.27098313
            }
        },
        {
            "label": 6,
            "probability": 0.999,
            "rect": {
                "bottom": 0.31245676,
                "left": 0.5376237,
                "right": 0.5376237,
                "top": 0.31245676
            }
        },
        {
            "label": 7,
            "probability": 0.999,
            "rect": {
                "bottom": 0.3153415,
                "left": 0.45953423,
                "right": 0.45953423,
                "top": 0.3153415
            }
        },
        {
            "label": 8,
            "probability": 0.999,
            "rect": {
                "bottom": 0.33976266,
                "left": 0.50074863,
                "right": 0.50074863,
                "top": 0.33976266
            }
        }
    ]
}