{
    "file_name": "000000408039.jpg",
    "generator": "convert_to_region_cropper.py",
    "labels": [
        "position",
        "left_eye",
        "right_eye",
        "left_cheek",
        "right_cheek",
        "nose_base",
        "left_mouth",
        "right_mouth",
        "bottom_mouth"
    ],
    "regions": [
        {
            "label": 0,
            "probability": 0.999,
            "rect": {
                "bottom": 0.33203125,
                "left": 0.5390625,
                "right": 0.68359375,
                "top": 0.1484375
            }
        },
        {
            "label": 1,
            "probability": 0.999,
            "rect": {
                "bottom": 0.24714056,
                "left": 0.61969036,
                "right": 0.61969036,
                "top": 0.24714056
            }
        },
        {
            "label": 2,
            "probability": 0.999,
            "rect": {
                "bottom": 0.24885857,
                "left": 0.5897253,
                "right": 0.5897253,
                "top": 0.24885857
            }
        },
        {
            "label": 3,
            "probability": 0.999,
            "rect": {
                "bottom": 0.2673124,
                "left": 0.55162036,
                "right": 0.55162036,
                "top": 0.2673124
            }
        },
        {
            "label": 5,
            "probability": 0.999,
            "rect": {
                "bottom": 0.27797315,
                "left": 0.61915034,
                "right": 0.61915034,
                "top": 0.27797315
            }
        },
        {
            "label": 7,
            "probability": 0.999,
            "rect": {
                "bottom": 0.2875623,
                "left": 0.59472406,
                "right": 0.59472406,
                "top": 0.2875623
            }
        },
        {
            "label": 8,
            "probability": 0.999,
            "rect": {
                "bottom": 0.29608327,
                "left": 0.61702365,
                "right": 0.61702365,
                "top": 0.29608327
            }
        }
    ]
}