{
    "file_name": "000000334557.jpg",
    "generator": "convert_to_region_cropper.py",
    "labels": [
        "position",
        "left_eye",
        "right_eye",
        "left_cheek",
        "right_cheek",
        "nose_base",
        "left_mouth",
        "right_mouth",
        "bottom_mouth"
    ],
    "regions": [
        {
            "label": 0,
            "probability": 0.999,
            "rect": {
                "bottom": 0.34375,
                "left": 0.40234375,
                "right": 0.58203125,
                "top": 0.12109375
            }
        },
        {
            "label": 1,
            "probability": 0.999,
            "rect": {
                "bottom": 0.23672153,
                "left": 0.52219576,
                "right": 0.52219576,
                "top": 0.23672153
            }
        },
        {
            "label": 2,
            "probability": 0.999,
            "rect": {
                "bottom": 0.23936379,
                "left": 0.4679701,
                "right": 0.4679701,
                "top": 0.23936379
            }
        },
        {
            "label": 3,
            "probability": 0.999,
            "rect": {
                "bottom": 0.27498877,
                "left": 0.4678244,
                "right": 0.4678244,
                "top": 0.27498877
            }
        },
        {
            "label": 4,
            "probability": 0.999,
            "rect": {
                "bottom": 0.2705194,
                "left": 0.52851844,
                "right": 0.52851844,
                "top": 0.2705194
            }
        },
        {
            "label": 5,
            "probability": 0.999,
            "rect": {
                "bottom": 0.28523558,
                "left": 0.49576247,
                "right": 0.49576247,
                "top": 0.28523558
            }
        },
        {
            "label": 6,
            "probability": 0.999,
            "rect": {
                "bottom": 0.30728632,
                "left": 0.5229785,
                "right": 0.5229785,
                "top": 0.30728632
            }
        },
        {
            "label": 7,
            "probability": 0.999,
            "rect": {
                "bottom": 0.310317,
                "left": 0.47835585,
                "right": 0.47835585,
                "top": 0.310317
            }
        },
        {
            "label": 8,
            "probability": 0.999,
            "rect": {
                "bottom": 0.32507446,
                "left": 0.4998985,
                "right": 0.4998985,
                "top": 0.32507446
            }
        },
        {
            "label": 0,
            "probability": 0.999,
            "rect": {
                "bottom": 0.60546875,
                "left": 0.3515625,
                "right": 0.59765625,
                "top": 0.30078125
            }
        },
        {
            "label": 1,
            "probability": 0.999,
            "rect": {
                "bottom": 0.46728888,
                "left": 0.5066941,
                "right": 0.5066941,
                "top": 0.46728888
            }
        },
        {
            "label": 2,
            "probability": 0.999,
            "rect": {
                "bottom": 0.44961524,
                "left": 0.45820302,
                "right": 0.45820302,
                "top": 0.44961524
            }
        },
        {
            "label": 4,
            "probability": 0.999,
            "rect": {
                "bottom": 0.5074869,
                "left": 0.56917673,
                "right": 0.56917673,
                "top": 0.5074869
            }
        },
        {
            "label": 6,
            "probability": 0.999,
            "rect": {
                "bottom": 0.565091,
                "left": 0.50230795,
                "right": 0.50230795,
                "top": 0.565091
            }
        },
        {
            "label": 8,
            "probability": 0.999,
            "rect": {
                "bottom": 0.5760813,
                "left": 0.462054,
                "right": 0.462054,
                "top": 0.5760813
            }
        }
    ]
}