{
    "file_name": "000000150184.jpg",
    "generator": "convert_to_region_cropper.py",
    "labels": [
        "position",
        "left_eye",
        "right_eye",
        "left_cheek",
        "right_cheek",
        "nose_base",
        "left_mouth",
        "right_mouth",
        "bottom_mouth"
    ],
    "regions": [
        {
            "label": 0,
            "probability": 0.999,
            "rect": {
                "bottom": 0.2982456,
                "left": 0.484375,
                "right": 0.625,
                "top": 0.040935673
            }
        },
        {
            "label": 1,
            "probability": 0.999,
            "rect": {
                "bottom": 0.17474039,
                "left": 0.58167434,
                "right": 0.58167434,
                "top": 0.17474039
            }
        },
        {
            "label": 2,
            "probability": 0.999,
            "rect": {
                "bottom": 0.18986134,
                "left": 0.5349411,
                "right": 0.5349411,
                "top": 0.18986134
            }
        },
        {
            "label": 3,
            "probability": 0.999,
            "rect": {
                "bottom": 0.22215225,
                "left": 0.53481126,
                "right": 0.53481126,
                "top": 0.22215225
            }
        },
        {
            "label": 4,
            "probability": 0.999,
            "rect": {
                "bottom": 0.20528233,
                "left": 0.5903094,
                "right": 0.5903094,
                "top": 0.20528233
            }
        },
        {
            "label": 5,
            "probability": 0.999,
            "rect": {
                "bottom": 0.22299473,
                "left": 0.5627544,
                "right": 0.5627544,
                "top": 0.22299473
            }
        },
        {
            "label": 6,
            "probability": 0.999,
            "rect": {
                "bottom": 0.23895197,
                "left": 0.5878343,
                "right": 0.5878343,
                "top": 0.23895197
            }
        },
        {
            "label": 7,
            "probability": 0.999,
            "rect": {
                "bottom": 0.25324178,
                "left": 0.54546344,
                "right": 0.54546344,
                "top": 0.25324178
            }
        },
        {
            "label": 8,
            "probability": 0.999,
            "rect": {
                "bottom": 0.26357794,
                "left": 0.57051027,
                "right": 0.57051027,
                "top": 0.26357794
            }
        },
        {
            "label": 0,
            "probability": 0.999,
            "rect": {
                "bottom": 0.5263158,
                "left": 0.32421875,
                "right": 0.44921875,
                "top": 0.28654972
            }
        },
        {
            "label": 1,
            "probability": 0.999,
            "rect": {
                "bottom": 0.40505588,
                "left": 0.41059202,
                "right": 0.41059202,
                "top": 0.40505588
            }
        },
        {
            "label": 2,
            "probability": 0.999,
            "rect": {
                "bottom": 0.4239818,
                "left": 0.36852035,
                "right": 0.36852035,
                "top": 0.4239818
            }
        },
        {
            "label": 3,
            "probability": 0.999,
            "rect": {
                "bottom": 0.4544004,
                "left": 0.3719259,
                "right": 0.3719259,
                "top": 0.4544004
            }
        },
        {
            "label": 4,
            "probability": 0.999,
            "rect": {
                "bottom": 0.43300682,
                "left": 0.42125073,
                "right": 0.42125073,
                "top": 0.43300682
            }
        },
        {
            "label": 5,
            "probability": 0.999,
            "rect": {
                "bottom": 0.45346785,
                "left": 0.39822167,
                "right": 0.39822167,
                "top": 0.45346785
            }
        },
        {
            "label": 6,
            "probability": 0.999,
            "rect": {
                "bottom": 0.4642358,
                "left": 0.4224832,
                "right": 0.4224832,
                "top": 0.4642358
            }
        },
        {
            "label": 7,
            "probability": 0.999,
            "rect": {
                "bottom": 0.4838338,
                "left": 0.3825782,
                "right": 0.3825782,
                "top": 0.4838338
            }
        },
        {
            "label": 8,
            "probability": 0.999,
            "rect": {
                "bottom": 0.49269006,
                "left": 0.4052887,
                "right": 0.4052887,
                "top": 0.49269006
            }
        }
    ]
}