{
    "created_at": "2018-09-06T14:46:11.174105",
    "file_name": "000000384159.jpg",
    "generator": "convert_to_region_cropper.py",
    "labels": [
        "position",
        "left_eye",
        "right_eye",
        "left_cheek",
        "right_cheek",
        "nose_base",
        "left_mouth",
        "right_mouth",
        "bottom_mouth"
    ],
    "regions": [
        {
            "label": 0,
            "probability": 0.999,
            "rect": {
                "bottom": 0.21875,
                "left": 0.09375,
                "right": 0.23828125,
                "top": 0.03515625
            }
        },
        {
            "label": 1,
            "probability": 0.999,
            "rect": {
                "bottom": 0.1452361,
                "left": 0.19307151,
                "right": 0.19307151,
                "top": 0.1452361
            }
        },
        {
            "label": 2,
            "probability": 0.999,
            "rect": {
                "bottom": 0.13660659,
                "left": 0.14784454,
                "right": 0.14784454,
                "top": 0.13660659
            }
        },
        {
            "label": 3,
            "probability": 0.999,
            "rect": {
                "bottom": 0.15480348,
                "left": 0.1149752,
                "right": 0.1149752,
                "top": 0.15480348
            }
        },
        {
            "label": 5,
            "probability": 0.999,
            "rect": {
                "bottom": 0.17935525,
                "left": 0.17812483,
                "right": 0.17812483,
                "top": 0.17935525
            }
        },
        {
            "label": 7,
            "probability": 0.999,
            "rect": {
                "bottom": 0.19265084,
                "left": 0.14488824,
                "right": 0.14488824,
                "top": 0.19265084
            }
        },
        {
            "label": 8,
            "probability": 0.999,
            "rect": {
                "bottom": 0.20856252,
                "left": 0.1756669,
                "right": 0.1756669,
                "top": 0.20856252
            }
        },
        {
            "label": 0,
            "probability": 0.999,
            "rect": {
                "bottom": 0.23828125,
                "left": 0.7578125,
                "right": 0.87890625,
                "top": 0.0859375
            }
        },
        {
            "label": 1,
            "probability": 0.999,
            "rect": {
                "bottom": 0.17014804,
                "left": 0.8395066,
                "right": 0.8395066,
                "top": 0.17014804
            }
        },
        {
            "label": 2,
            "probability": 0.999,
            "rect": {
                "bottom": 0.17043711,
                "left": 0.8031187,
                "right": 0.8031187,
                "top": 0.17043711
            }
        },
        {
            "label": 3,
            "probability": 0.999,
            "rect": {
                "bottom": 0.18963076,
                "left": 0.80191606,
                "right": 0.80191606,
                "top": 0.18963076
            }
        },
        {
            "label": 4,
            "probability": 0.999,
            "rect": {
                "bottom": 0.18669933,
                "left": 0.8417809,
                "right": 0.8417809,
                "top": 0.18669933
            }
        },
        {
            "label": 5,
            "probability": 0.999,
            "rect": {
                "bottom": 0.19797076,
                "left": 0.82342505,
                "right": 0.82342505,
                "top": 0.19797076
            }
        },
        {
            "label": 6,
            "probability": 0.999,
            "rect": {
                "bottom": 0.20608985,
                "left": 0.8378957,
                "right": 0.8378957,
                "top": 0.20608985
            }
        },
        {
            "label": 7,
            "probability": 0.999,
            "rect": {
                "bottom": 0.20845768,
                "left": 0.8074173,
                "right": 0.8074173,
                "top": 0.20845768
            }
        },
        {
            "label": 8,
            "probability": 0.999,
            "rect": {
                "bottom": 0.21750203,
                "left": 0.823425,
                "right": 0.823425,
                "top": 0.21750203
            }
        }
    ]
}