{
    "created_at": "2018-09-06T14:46:30.698751",
    "file_name": "000000472845.jpg",
    "generator": "convert_to_region_cropper.py",
    "labels": [
        "position",
        "left_eye",
        "right_eye",
        "left_cheek",
        "right_cheek",
        "nose_base",
        "left_mouth",
        "right_mouth",
        "bottom_mouth"
    ],
    "regions": [
        {
            "label": 0,
            "probability": 0.999,
            "rect": {
                "bottom": 0.6640625,
                "left": 0.25,
                "right": 0.69140625,
                "top": 0.11328125
            }
        },
        {
            "label": 2,
            "probability": 0.999,
            "rect": {
                "bottom": 0.410802,
                "left": 0.4156011,
                "right": 0.4156011,
                "top": 0.410802
            }
        },
        {
            "label": 3,
            "probability": 0.999,
            "rect": {
                "bottom": 0.46428394,
                "left": 0.4142251,
                "right": 0.4142251,
                "top": 0.46428394
            }
        },
        {
            "label": 6,
            "probability": 0.999,
            "rect": {
                "bottom": 0.5196959,
                "left": 0.59850043,
                "right": 0.59850043,
                "top": 0.5196959
            }
        },
        {
            "label": 7,
            "probability": 0.999,
            "rect": {
                "bottom": 0.52214175,
                "left": 0.43115592,
                "right": 0.43115592,
                "top": 0.52214175
            }
        },
        {
            "label": 8,
            "probability": 0.999,
            "rect": {
                "bottom": 0.54821885,
                "left": 0.48104087,
                "right": 0.48104087,
                "top": 0.54821885
            }
        }
    ]
}