{
    "created_at": "2018-09-06T14:46:14.600121",
    "file_name": "000000401444.jpg",
    "generator": "convert_to_region_cropper.py",
    "labels": [
        "position",
        "left_eye",
        "right_eye",
        "left_cheek",
        "right_cheek",
        "nose_base",
        "left_mouth",
        "right_mouth",
        "bottom_mouth"
    ],
    "regions": [
        {
            "label": 0,
            "probability": 0.999,
            "rect": {
                "bottom": 0.453125,
                "left": 0.3671875,
                "right": 0.69921875,
                "top": 0.03515625
            }
        },
        {
            "label": 1,
            "probability": 0.999,
            "rect": {
                "bottom": 0.25823626,
                "left": 0.57099015,
                "right": 0.57099015,
                "top": 0.25823626
            }
        },
        {
            "label": 2,
            "probability": 0.999,
            "rect": {
                "bottom": 0.25565767,
                "left": 0.48673832,
                "right": 0.48673832,
                "top": 0.25565767
            }
        },
        {
            "label": 3,
            "probability": 0.999,
            "rect": {
                "bottom": 0.28722706,
                "left": 0.4355819,
                "right": 0.4355819,
                "top": 0.28722706
            }
        },
        {
            "label": 5,
            "probability": 0.999,
            "rect": {
                "bottom": 0.3389177,
                "left": 0.5494959,
                "right": 0.5494959,
                "top": 0.3389177
            }
        },
        {
            "label": 7,
            "probability": 0.999,
            "rect": {
                "bottom": 0.37427354,
                "left": 0.49224028,
                "right": 0.49224028,
                "top": 0.37427354
            }
        },
        {
            "label": 8,
            "probability": 0.999,
            "rect": {
                "bottom": 0.39815632,
                "left": 0.54599714,
                "right": 0.54599714,
                "top": 0.39815632
            }
        }
    ]
}