{
    "created_at": "2018-09-06T14:46:21.329969",
    "file_name": "000000430300.jpg",
    "generator": "convert_to_region_cropper.py",
    "labels": [
        "position",
        "left_eye",
        "right_eye",
        "left_cheek",
        "right_cheek",
        "nose_base",
        "left_mouth",
        "right_mouth",
        "bottom_mouth"
    ],
    "regions": [
        {
            "label": 0,
            "probability": 0.999,
            "rect": {
                "bottom": 0.48046875,
                "left": 0.44140625,
                "right": 0.5859375,
                "top": 0.30078125
            }
        },
        {
            "label": 2,
            "probability": 0.999,
            "rect": {
                "bottom": 0.4098905,
                "left": 0.51919395,
                "right": 0.51919395,
                "top": 0.4098905
            }
        },
        {
            "label": 3,
            "probability": 0.999,
            "rect": {
                "bottom": 0.40248176,
                "left": 0.483967,
                "right": 0.483967,
                "top": 0.40248176
            }
        },
        {
            "label": 5,
            "probability": 0.999,
            "rect": {
                "bottom": 0.43054938,
                "left": 0.51051015,
                "right": 0.51051015,
                "top": 0.43054938
            }
        },
        {
            "label": 7,
            "probability": 0.999,
            "rect": {
                "bottom": 0.43694094,
                "left": 0.49336585,
                "right": 0.49336585,
                "top": 0.43694094
            }
        }
    ]
}