{
    "created_at": "2018-09-06T14:45:35.443383",
    "file_name": "000000227943.jpg",
    "generator": "convert_to_region_cropper.py",
    "labels": [
        "position",
        "left_eye",
        "right_eye",
        "left_cheek",
        "right_cheek",
        "nose_base",
        "left_mouth",
        "right_mouth",
        "bottom_mouth"
    ],
    "regions": [
        {
            "label": 0,
            "probability": 0.999,
            "rect": {
                "bottom": 0.4765625,
                "left": 0.44921875,
                "right": 0.81640625,
                "top": 0.015625
            }
        },
        {
            "label": 1,
            "probability": 0.999,
            "rect": {
                "bottom": 0.26921535,
                "left": 0.7041449,
                "right": 0.7041449,
                "top": 0.26921535
            }
        },
        {
            "label": 2,
            "probability": 0.999,
            "rect": {
                "bottom": 0.24251886,
                "left": 0.5569914,
                "right": 0.5569914,
                "top": 0.24251886
            }
        },
        {
            "label": 3,
            "probability": 0.999,
            "rect": {
                "bottom": 0.31403893,
                "left": 0.5403569,
                "right": 0.5403569,
                "top": 0.31403893
            }
        },
        {
            "label": 4,
            "probability": 0.999,
            "rect": {
                "bottom": 0.32788202,
                "left": 0.69944793,
                "right": 0.69944793,
                "top": 0.32788202
            }
        },
        {
            "label": 5,
            "probability": 0.999,
            "rect": {
                "bottom": 0.33095652,
                "left": 0.6173225,
                "right": 0.6173225,
                "top": 0.33095652
            }
        },
        {
            "label": 6,
            "probability": 0.999,
            "rect": {
                "bottom": 0.39102978,
                "left": 0.6621876,
                "right": 0.6621876,
                "top": 0.39102978
            }
        },
        {
            "label": 7,
            "probability": 0.999,
            "rect": {
                "bottom": 0.3765577,
                "left": 0.54743034,
                "right": 0.54743034,
                "top": 0.3765577
            }
        },
        {
            "label": 8,
            "probability": 0.999,
            "rect": {
                "bottom": 0.4094331,
                "left": 0.5979771,
                "right": 0.5979771,
                "top": 0.4094331
            }
        }
    ]
}