{
    "created_at": "2018-09-06T14:46:13.335011",
    "file_name": "000000395475.jpg",
    "generator": "convert_to_region_cropper.py",
    "labels": [
        "position",
        "left_eye",
        "right_eye",
        "left_cheek",
        "right_cheek",
        "nose_base",
        "left_mouth",
        "right_mouth",
        "bottom_mouth"
    ],
    "regions": [
        {
            "label": 0,
            "probability": 0.999,
            "rect": {
                "bottom": 0.28515625,
                "left": 0.66796875,
                "right": 0.7734375,
                "top": 0.15234375
            }
        },
        {
            "label": 1,
            "probability": 0.999,
            "rect": {
                "bottom": 0.23026498,
                "left": 0.74072415,
                "right": 0.74072415,
                "top": 0.23026498
            }
        },
        {
            "label": 2,
            "probability": 0.999,
            "rect": {
                "bottom": 0.21767259,
                "left": 0.70746803,
                "right": 0.70746803,
                "top": 0.21767259
            }
        },
        {
            "label": 3,
            "probability": 0.999,
            "rect": {
                "bottom": 0.23528282,
                "left": 0.6994773,
                "right": 0.6994773,
                "top": 0.23528282
            }
        },
        {
            "label": 4,
            "probability": 0.999,
            "rect": {
                "bottom": 0.25242007,
                "left": 0.7397422,
                "right": 0.7397422,
                "top": 0.25242007
            }
        },
        {
            "label": 5,
            "probability": 0.999,
            "rect": {
                "bottom": 0.25219035,
                "left": 0.71746653,
                "right": 0.71746653,
                "top": 0.25219035
            }
        },
        {
            "label": 6,
            "probability": 0.999,
            "rect": {
                "bottom": 0.27359337,
                "left": 0.73069084,
                "right": 0.73069084,
                "top": 0.27359337
            }
        },
        {
            "label": 7,
            "probability": 0.999,
            "rect": {
                "bottom": 0.26072752,
                "left": 0.7015003,
                "right": 0.7015003,
                "top": 0.26072752
            }
        },
        {
            "label": 8,
            "probability": 0.999,
            "rect": {
                "bottom": 0.27519348,
                "left": 0.713999,
                "right": 0.713999,
                "top": 0.27519348
            }
        }
    ]
}