{
    "created_at": "2018-09-06T14:44:59.657297",
    "file_name": "000000073682.jpg",
    "generator": "convert_to_region_cropper.py",
    "labels": [
        "position",
        "left_eye",
        "right_eye",
        "left_cheek",
        "right_cheek",
        "nose_base",
        "left_mouth",
        "right_mouth",
        "bottom_mouth"
    ],
    "regions": [
        {
            "label": 0,
            "probability": 0.999,
            "rect": {
                "bottom": 0.44140625,
                "left": 0.453125,
                "right": 0.56640625,
                "top": 0.296875
            }
        },
        {
            "label": 1,
            "probability": 0.999,
            "rect": {
                "bottom": 0.377327,
                "left": 0.52565414,
                "right": 0.52565414,
                "top": 0.377327
            }
        },
        {
            "label": 2,
            "probability": 0.999,
            "rect": {
                "bottom": 0.37602726,
                "left": 0.49524513,
                "right": 0.49524513,
                "top": 0.37602726
            }
        },
        {
            "label": 3,
            "probability": 0.999,
            "rect": {
                "bottom": 0.38511294,
                "left": 0.4748084,
                "right": 0.4748084,
                "top": 0.38511294
            }
        },
        {
            "label": 5,
            "probability": 0.999,
            "rect": {
                "bottom": 0.4054753,
                "left": 0.5166008,
                "right": 0.5166008,
                "top": 0.4054753
            }
        },
        {
            "label": 7,
            "probability": 0.999,
            "rect": {
                "bottom": 0.41212583,
                "left": 0.49532384,
                "right": 0.49532384,
                "top": 0.41212583
            }
        },
        {
            "label": 8,
            "probability": 0.999,
            "rect": {
                "bottom": 0.42206967,
                "left": 0.51361454,
                "right": 0.51361454,
                "top": 0.42206967
            }
        },
        {
            "label": 0,
            "probability": 0.999,
            "rect": {
                "bottom": 0.3359375,
                "left": 0.25390625,
                "right": 0.4453125,
                "top": 0.09765625
            }
        },
        {
            "label": 1,
            "probability": 0.999,
            "rect": {
                "bottom": 0.22701979,
                "left": 0.362152,
                "right": 0.362152,
                "top": 0.22701979
            }
        },
        {
            "label": 2,
            "probability": 0.999,
            "rect": {
                "bottom": 0.22435024,
                "left": 0.3213494,
                "right": 0.3213494,
                "top": 0.22435024
            }
        },
        {
            "label": 3,
            "probability": 0.999,
            "rect": {
                "bottom": 0.25256172,
                "left": 0.2983296,
                "right": 0.2983296,
                "top": 0.25256172
            }
        },
        {
            "label": 5,
            "probability": 0.999,
            "rect": {
                "bottom": 0.2729086,
                "left": 0.35422128,
                "right": 0.35422128,
                "top": 0.2729086
            }
        },
        {
            "label": 7,
            "probability": 0.999,
            "rect": {
                "bottom": 0.28689605,
                "left": 0.32473367,
                "right": 0.32473367,
                "top": 0.28689605
            }
        },
        {
            "label": 8,
            "probability": 0.999,
            "rect": {
                "bottom": 0.30009666,
                "left": 0.35468924,
                "right": 0.35468924,
                "top": 0.30009666
            }
        }
    ]
}